cli.py
vodafone_station_cli-0.1.0.dist-info/licenses/LICENSE
vodafone_station_cli-0.1.0.dist-info/METADATA
vodafone_station_cli-0.1.0.dist-info/WHEEL
vodafone_station_cli-0.1.0.dist-info/entry_points.txt
vodafone_station_cli-0.1.0.dist-info/top_level.txt
vodafone_station_cli-0.1.0.dist-info/RECORD
