Metadata-Version: 2.4
Name: vodafone-station-cli
Version: 0.1.0
Summary: CLI for interacting with a Vodafone Station
Author-email: Philipp Schmitt <philipp@schmitt.co>
License:                     GNU GENERAL PUBLIC LICENSE
Project-URL: homepage, https://github.com/pschmitt/vodafone-station-cli
Project-URL: documentation, https://github.com/pschmitt/vodafone-station-cli/blob/head/readme.md
Project-URL: repository, https://github.com/pschmitt/vodafone-station-cli
Project-URL: issues, https://github.com/pschmitt/vodafone-station-cli/issues
Keywords: voadafone,vodafone-station
Classifier: Programming Language :: Python :: 3
Requires-Python: >=3.13
License-File: LICENSE
Requires-Dist: aiovodafone>=1.1.0
Requires-Dist: rich>=14.0.0
Dynamic: license-file
